ndicom_cuda_kmeans/__init__.py
ndicom_cuda_kmeans/plugin.py
ndicom_cuda_kmeans-0.0.1.dev1.dist-info/METADATA
ndicom_cuda_kmeans-0.0.1.dev1.dist-info/RECORD
ndicom_cuda_kmeans-0.0.1.dev1.dist-info/WHEEL
ndicom_cuda_kmeans-0.0.1.dev1.dist-info/dependency_links.txt
ndicom_cuda_kmeans-0.0.1.dev1.dist-info/top_level.txt
